anndb
