Metadata-Version: 1.1
Name: anndb
Version: 0.0.4
Summary: AnnDB Client
Home-page: https://github.com/marekgalovic/anndb-client-python
Author: Marek Galovic
Author-email: galovic.galovic@gmail.com
License: MIT
Download-URL: https://github.com/marekgalovic/anndb-client-python/archive/0.0.4.tar.gz
Platform: UNKNOWN
